CHANGELOG.txt
LICENSE.txt
MANIFEST.in
README.txt
VERSION.txt
setup.py
doc/Makefile
doc/checks.rst
doc/conf.py
doc/core.rst
doc/index.rst
doc/types.rst
formalize/__init__.py
formalize/checks.py
formalize/core.py
formalize/types.py
formalize/unpack.py
formalize.egg-info/PKG-INFO
formalize.egg-info/SOURCES.txt
formalize.egg-info/dependency_links.txt
formalize.egg-info/entry_points.txt
formalize.egg-info/not-zip-safe
formalize.egg-info/top_level.txt