Metadata-Version: 1.0
Name: formalize
Version: 0.1.3
Summary: Form processing and validation
Home-page: http://ollycope.com/software/formalize/
Author: Oliver Cope
Author-email: oliver@redgecko.org
License: BSD
Platform: UNKNOWN
Classifier: Development Status :: 3 - Alpha
Classifier: Environment :: Web Environment
Classifier: Intended Audience :: Developers
Classifier: License :: OSI Approved :: BSD License
Classifier: Operating System :: OS Independent
Classifier: Programming Language :: Python
Classifier: Topic :: Internet :: WWW/HTTP
Classifier: Topic :: Software Development :: Libraries :: Python Modules
